lyyddforward
